<?xml version="1.0" encoding="utf-8" ?><dwsync><file name="search.test" server="theteapot.me.uk/subdomains/pentafoods/httpdocs/" local="3415014698" remote="16308977688" /><file name="search.pages.inc" server="theteapot.me.uk/subdomains/pentafoods/httpdocs/" local="3415014698" remote="16308977688" /><file name="search.module" server="theteapot.me.uk/subdomains/pentafoods/httpdocs/" local="3415014698" remote="16308977688" /><file name="search.install" server="theteapot.me.uk/subdomains/pentafoods/httpdocs/" local="3415014698" remote="16308977688" /><file name="search.info" server="theteapot.me.uk/subdomains/pentafoods/httpdocs/" local="3415014698" remote="16308977688" /><file name="search.extender.inc" server="theteapot.me.uk/subdomains/pentafoods/httpdocs/" local="3415014698" remote="16308977688" /><file name="search.css" server="theteapot.me.uk/subdomains/pentafoods/httpdocs/" local="3415014698" remote="16308977688" /><file name="search.api.php" server="theteapot.me.uk/subdomains/pentafoods/httpdocs/" local="3415014698" remote="16308977688" /><file name="search.admin.inc" server="theteapot.me.uk/subdomains/pentafoods/httpdocs/" local="3415014698" remote="16308977748" /><file name="search-rtl.css" server="theteapot.me.uk/subdomains/pentafoods/httpdocs/" local="3415014698" remote="16308977748" /><file name="search-results.tpl.php" server="theteapot.me.uk/subdomains/pentafoods/httpdocs/" local="3415014698" remote="16308977748" /><file name="search-result.tpl.php" server="theteapot.me.uk/subdomains/pentafoods/httpdocs/" local="3415014698" remote="16308977748" /><file name="search-block-form.tpl.php" server="theteapot.me.uk/subdomains/pentafoods/httpdocs/" local="3415014698" remote="16308977748" /></dwsync>