<?xml version="1.0" encoding="utf-8" ?><dwsync><file name="overlay.tpl.php" server="theteapot.me.uk/subdomains/pentafoods/httpdocs/" local="3415014698" remote="16308977928" /><file name="overlay.module" server="theteapot.me.uk/subdomains/pentafoods/httpdocs/" local="3415014698" remote="16308977928" /><file name="overlay.install" server="theteapot.me.uk/subdomains/pentafoods/httpdocs/" local="3415014698" remote="16308977928" /><file name="overlay.info" server="theteapot.me.uk/subdomains/pentafoods/httpdocs/" local="3415014698" remote="16308977928" /><file name="overlay.api.php" server="theteapot.me.uk/subdomains/pentafoods/httpdocs/" local="3415014698" remote="16308977928" /><file name="overlay-parent.js" server="theteapot.me.uk/subdomains/pentafoods/httpdocs/" local="3415014698" remote="16308977928" /><file name="overlay-parent.css" server="theteapot.me.uk/subdomains/pentafoods/httpdocs/" local="3415014698" remote="16308977928" /><file name="overlay-child.js" server="theteapot.me.uk/subdomains/pentafoods/httpdocs/" local="3415014698" remote="16308977928" /><file name="overlay-child.css" server="theteapot.me.uk/subdomains/pentafoods/httpdocs/" local="3415014698" remote="16308977928" /><file name="overlay-child-rtl.css" server="theteapot.me.uk/subdomains/pentafoods/httpdocs/" local="3415014698" remote="16308977928" /></dwsync>